cointanalysis/__init__.py
cointanalysis/_aeg_pca.py
cointanalysis/_stat.py
cointanalysis/_utils.py
cointanalysis/coint.py
cointanalysis/ou.py
cointanalysis-0.3.5.dist-info/LICENSE
cointanalysis-0.3.5.dist-info/METADATA
cointanalysis-0.3.5.dist-info/WHEEL
cointanalysis-0.3.5.dist-info/RECORD
