Metadata-Version: 2.1
Name: cointanalysis
Version: 0.3.5
Summary: Python package for cointegration analysis.
License: BSD-3-Clause
Author: Shota Imaki
Author-email: shota.imaki.0801@gmail.com
Requires-Python: >=3.6.13,<4.0.0
Classifier: License :: OSI Approved :: BSD License
Classifier: Programming Language :: Python :: 3
Classifier: Programming Language :: Python :: 3.7
Classifier: Programming Language :: Python :: 3.8
Classifier: Programming Language :: Python :: 3.9
Classifier: Programming Language :: Python :: 3.10
Classifier: Programming Language :: Python :: 3.11
Requires-Dist: numpy (>=1.19.0,<2.0.0)
Requires-Dist: scikit-learn (>=0.23,<0.25)
Requires-Dist: statsmodels (>=0.13.4,<0.14.0)
